calendar_agent/__init__.py
calendar_agent/main.py
calendar_agent-1.0.1.dist-info/LICENSE
calendar_agent-1.0.1.dist-info/METADATA
calendar_agent-1.0.1.dist-info/WHEEL
calendar_agent-1.0.1.dist-info/RECORD
